xia_engine_terraform/__init__.py
xia_engine_terraform/engine.cp311-win_amd64.pyd
xia_engine_terraform-0.1.20.dist-info/LICENSE.txt
xia_engine_terraform-0.1.20.dist-info/METADATA
xia_engine_terraform-0.1.20.dist-info/WHEEL
xia_engine_terraform-0.1.20.dist-info/top_level.txt
xia_engine_terraform-0.1.20.dist-info/RECORD
