Metadata-Version: 2.1
Name: xia-engine-terraform
Version: 0.1.20
Home-page: https://develop.x-i-a.com/docs/xia-engine-terraform/0.1.20/index.html
Author: X-I-A
Author-email: admin@x-i-a.com
Requires-Python: >=3.9
License-File: LICENSE.txt
Requires-Dist: jinja2
Requires-Dist: requests
Requires-Dist: xia-engine
